airflow_provider_weights_and_biases/__init__.py
airflow_provider_weights_and_biases/hooks/__init__.py
airflow_provider_weights_and_biases/operators/__init__.py
airflow_provider_weights_and_biases/sensors/__init__.py
airflow_provider_weights_and_biases/triggers/__init__.py
airflow_provider_weights_and_biases-0.0.0a0.dist-info/LICENSE.txt
airflow_provider_weights_and_biases-0.0.0a0.dist-info/METADATA
airflow_provider_weights_and_biases-0.0.0a0.dist-info/WHEEL
airflow_provider_weights_and_biases-0.0.0a0.dist-info/top_level.txt
airflow_provider_weights_and_biases-0.0.0a0.dist-info/RECORD
